xiaocui/__init__.py
xiaocui/xiaocui.py
xiaocui-0.0.2.dist-info/LICENSE
xiaocui-0.0.2.dist-info/METADATA
xiaocui-0.0.2.dist-info/WHEEL
xiaocui-0.0.2.dist-info/top_level.txt
xiaocui-0.0.2.dist-info/RECORD
