Metadata-Version: 2.1
Name: xiaocui
Version: 0.0.2
Summary: This is an cui package, fa li wu bian
Home-page: https://github.com/cuiyonghua6/cui_package
Author: xiaocui
Author-email: cui_yonghua6@163.com
License: UNKNOWN
Keywords: hello world example examples
Platform: UNKNOWN
Classifier: Programming Language :: Python :: 3
Classifier: License :: OSI Approved :: MIT License
Classifier: Operating System :: OS Independent
